hackmudChat_package_test.py
hackmudchat_package_test-0.0.1.dist-info/licenses/LICENSE
hackmudchat_package_test-0.0.1.dist-info/WHEEL
hackmudchat_package_test-0.0.1.dist-info/METADATA
hackmudchat_package_test-0.0.1.dist-info/RECORD
