Metadata-Version: 2.4
Name: hackmudChat_package_test
Version: 0.0.1
Summary: A python implementation of the hackmud chat API, using the requests module.
Author-email: jckirton <author@example.com>
License-Expression: GPL-3.0-or-later
License-File: LICENSE
